box_pleating/__init__.py
box_pleating/geometry.py
box_pleating/grid_operations.py
box_pleating/models.py
box_pleating/pattern.py
box_pleating/theorems.py
box_pleating/fold/__init__.py
box_pleating/fold/converter.py
box_pleating/fold/geometry.py
box_pleating/fold/grid.py
box_pleating-1.0.1.dist-info/METADATA
box_pleating-1.0.1.dist-info/WHEEL
box_pleating-1.0.1.dist-info/licenses/LICENSE
box_pleating-1.0.1.dist-info/RECORD
