Metadata-Version: 2.3
Name: box-pleating
Version: 1.0.1
Summary: Box pleating crease pattern creation and flat-foldability with FOLD file import/export
Project-URL: Homepage, https://github.com/Googolplexic/box-pleating
Project-URL: Issues, https://github.com/Googolplexic/box-pleating/issues
Author-email: Coleman Lai <colemancflai@yahoo.com>
License-File: LICENSE
Classifier: License :: OSI Approved :: MIT License
Classifier: Operating System :: OS Independent
Classifier: Programming Language :: Python :: 3
Requires-Python: >=3.8
Requires-Dist: numpy
